<?xml version="1.0" encoding="utf-8" standalone="no"?>
<!DOCTYPE outline PUBLIC "-//omnigroup.com//DTD OUTLINE 3.0//EN" "http://www.omnigroup.com/namespace/OmniOutliner/xmloutline-v3.dtd">
<outline xmlns="http://www.omnigroup.com/namespace/OmniOutliner/v3"><columns><column is-outline-column="no" id=":0" is-note-column="yes" maximum-width="1000000" minimum-width="13" prints="yes" sort="none" status-sort="none" text-export-width="40" width="100" type="text"><title><text><p><run/></p></text></title></column><column is-outline-column="yes" id=":1" is-note-column="no" maximum-width="1000000" minimum-width="13" prints="yes" sort="none" status-sort="none" text-export-width="40" width="200" type="text"><title><text><p><run><lit>Title</lit></run></p></text></title></column></columns><root><item children-are-sections="no" expanded="yes" state="unchecked"><style><value key="text-background-color"><color r="1" g="1" b="1"/></value></style><values><text><p><run><lit>Jack</lit></run></p></text></values><children><item children-are-sections="no" expanded="yes" state="unchecked"><style><value key="text-background-color"><color r="1" g="1" b="1"/></value></style><values><text><p><run><lit>To</lit></run></p></text></values><children><item children-are-sections="no" expanded="yes" state="unchecked"><style><value key="text-background-color"><color r="1" g="1" b="1"/></value></style><values><text><p><run><lit>Jack</lit></run></p></text></values></item></children><children><item children-are-sections="no" expanded="yes" state="unchecked"><style><value key="text-background-color"><color r="1" g="1" b="1"/></value></style><values><text><p><run><lit>Fell</lit></run></p></text></values></item></children><children><item children-are-sections="no" expanded="yes" state="unchecked"><style><value key="text-background-color"><color r="1" g="1" b="1"/></value></style><values><text><p><run><lit>Down</lit></run></p></text></values><children><item children-are-sections="no" expanded="yes" state="unchecked"><style><value key="text-background-color"><color r="1" g="1" b="1"/></value></style><values><text><p><run><style><value key="font-family">Helvetica</value><value key="font-size">12.000000</value><value key="font-fill"><color w="0"/></value></style><lit>The</lit></run></p></text></values></item></children><children><item children-are-sections="no" expanded="yes" state="unchecked"><style><value key="text-background-color"><color r="1" g="1" b="1"/></value></style><values><text><p><run><style><value key="font-family">Helvetica</value><value key="font-size">12.000000</value><value key="font-fill"><color w="0"/></value></style><lit>Rabbit</lit></run></p></text></values><children><item children-are-sections="no" expanded="yes" state="unchecked"><style><value key="text-background-color"><color r="1" g="1" b="1"/></value></style><values><text><p><run><style><value key="font-family">Helvetica</value><value key="font-size">12.000000</value><value key="font-fill"><color w="0"/></value></style><lit>Hole</lit></run></p></text></values></item></children></item></children></item></children><children><item children-are-sections="no" expanded="yes" state="unchecked"><style><value key="text-background-color"><color r="1" g="1" b="1"/></value></style><values><text><p><run><lit>And</lit></run></p></text></values></item></children><children><item children-are-sections="no" expanded="yes" state="unchecked"><style><value key="text-background-color"><color r="1" g="1" b="1"/></value></style><values><text><p><run><lit>Broke</lit></run></p></text></values></item></children><children><item children-are-sections="no" expanded="yes" state="unchecked"><style><value key="text-background-color"><color r="1" g="1" b="1"/></value></style><values><text><p><run><lit>His</lit></run></p></text></values></item></children><children><item children-are-sections="no" expanded="yes" state="unchecked"><style><value key="text-background-color"><color r="1" g="1" b="1"/></value></style><values><text><p><run><lit>Crown</lit></run></p></text></values><children><item children-are-sections="no" expanded="yes" state="unchecked"><style><value key="text-background-color"><color r="1" g="1" b="1"/></value></style><values><text><p><run><lit>And</lit></run></p></text></values></item></children><children><item children-are-sections="no" expanded="yes" state="unchecked"><style><value key="text-background-color"><color r="1" g="1" b="1"/></value></style><values><text><p><run><lit>Jill</lit></run></p></text></values></item></children><children><item children-are-sections="no" expanded="yes" state="unchecked"><style><value key="text-background-color"><color r="1" g="1" b="1"/></value></style><values><text><p><run><lit>Came</lit></run></p></text></values></item></children><children><item children-are-sections="no" expanded="yes" state="unchecked"><style><value key="text-background-color"><color r="1" g="1" b="1"/></value></style><values><text><p><run><lit>Tumbling</lit></run></p></text></values></item></children><children><item children-are-sections="no" expanded="yes" state="unchecked"><style><value key="text-background-color"><color r="1" g="1" b="1"/></value></style><values><text><p><run><lit>After</lit></run></p></text></values><children><item children-are-sections="no" expanded="yes" state="unchecked"><style><value key="text-background-color"><color r="1" g="1" b="1"/></value></style><values><text><p><run><lit>Up</lit></run></p></text></values></item></children><children><item children-are-sections="no" expanded="yes" state="unchecked"><style><value key="text-background-color"><color r="1" g="1" b="1"/></value></style><values><text><p><run><lit>Jack</lit></run></p></text></values></item></children><children><item children-are-sections="no" expanded="yes" state="unchecked"><style><value key="text-background-color"><color r="1" g="1" b="1"/></value></style><values><text><p><run><lit>Got</lit></run></p></text></values></item></children><children><item children-are-sections="no" expanded="yes" state="unchecked"><style><value key="text-background-color"><color r="1" g="1" b="1"/></value></style><values><text><p><run><lit>And</lit></run></p></text></values></item></children><children><item children-are-sections="no" expanded="yes" state="unchecked"><style><value key="text-background-color"><color r="1" g="1" b="1"/></value></style><values><text><p><run><lit>Home</lit></run></p></text></values></item></children><children><item children-are-sections="no" expanded="yes" state="unchecked"><style><value key="text-background-color"><color r="1" g="1" b="1"/></value></style><values><text><p><run><lit>Did</lit></run></p></text></values></item></children><children><item children-are-sections="no" expanded="yes" state="unchecked"><style><value key="text-background-color"><color r="1" g="1" b="1"/></value></style><values><text><p><run><lit>Trot</lit></run></p></text></values><children><item children-are-sections="no" expanded="yes" state="unchecked"><style><value key="text-background-color"><color r="1" g="1" b="1"/></value></style><values><text><p><run><lit>As</lit></run></p></text></values></item></children><children><item children-are-sections="no" expanded="yes" state="unchecked"><style><value key="text-background-color"><color r="1" g="1" b="1"/></value></style><values><text><p><run><lit>Fast</lit></run></p></text></values></item></children><children><item children-are-sections="no" expanded="yes" state="unchecked"><style><value key="text-background-color"><color r="1" g="1" b="1"/></value></style><values><text><p><run><lit>As</lit></run></p></text></values></item></children><children><item children-are-sections="no" expanded="yes" state="unchecked"><style><value key="text-background-color"><color r="1" g="1" b="1"/></value></style><values><text><p><run><lit>He</lit></run></p></text></values></item></children><children><item children-are-sections="no" expanded="yes" state="unchecked"><style><value key="text-background-color"><color r="1" g="1" b="1"/></value></style><values><text><p><run><lit>Could</lit></run></p></text></values></item></children><children><item children-are-sections="no" expanded="yes" state="unchecked"><style><value key="text-background-color"><color r="1" g="1" b="1"/></value></style><values><text><p><run><lit>Caper</lit></run></p></text></values><children><item children-are-sections="no" expanded="yes" state="unchecked"><style><value key="text-background-color"><color r="1" g="1" b="1"/></value></style><values><text><p><run><lit>To</lit></run></p></text></values></item></children><children><item children-are-sections="no" expanded="yes" state="unchecked"><style><value key="text-background-color"><color r="1" g="1" b="1"/></value></style><values><text><p><run><lit>Old</lit></run></p></text></values></item></children><children><item children-are-sections="no" expanded="yes" state="unchecked"><style><value key="text-background-color"><color r="1" g="1" b="1"/></value></style><values><text><p><run><lit>Dame</lit></run></p></text></values></item></children><children><item children-are-sections="no" expanded="yes" state="unchecked"><style><value key="text-background-color"><color r="1" g="1" b="1"/></value></style><values><text><p><run><lit>Dob</lit></run></p></text></values></item></children><children><item children-are-sections="no" expanded="yes" state="unchecked"><style><value key="text-background-color"><color r="1" g="1" b="1"/></value></style><values><text><p><run><lit>Who</lit></run></p></text></values></item></children><children><item children-are-sections="no" expanded="yes" state="unchecked"><style><value key="text-background-color"><color r="1" g="1" b="1"/></value></style><values><text><p><run><lit>Patched</lit></run></p></text></values></item></children><children><item children-are-sections="no" expanded="yes" state="unchecked"><style><value key="text-background-color"><color r="1" g="1" b="1"/></value></style><values><text><p><run><lit>His</lit></run></p></text></values></item></children><children><item children-are-sections="no" expanded="yes" state="unchecked"><style><value key="text-background-color"><color r="1" g="1" b="1"/></value></style><values><text><p><run><lit>Nob</lit></run></p></text></values><children><item children-are-sections="no" expanded="yes" state="unchecked"><style><value key="text-background-color"><color r="1" g="1" b="1"/></value></style><values><text><p><run><lit>With</lit></run></p></text></values></item></children><children><item children-are-sections="no" expanded="yes" state="unchecked"><style><value key="text-background-color"><color r="1" g="1" b="1"/></value></style><values><text><p><run><lit>Vinegar</lit></run></p></text></values></item></children><children><item children-are-sections="no" expanded="yes" state="unchecked"><style><value key="text-background-color"><color r="1" g="1" b="1"/></value></style><values><text><p><run><lit>And</lit></run></p></text></values></item></children><children><item children-are-sections="no" expanded="yes" state="unchecked"><style><value key="text-background-color"><color r="1" g="1" b="1"/></value></style><values><text><p><run><lit>Brown</lit></run></p></text></values><children><item children-are-sections="no" expanded="yes" state="unchecked"><style><value key="text-background-color"><color r="1" g="1" b="1"/></value></style><values><text><p><run><lit>Paper</lit></run></p></text></values></item></children></item></children></item></children></item></children></item></children></item></children></item></children></item></children><children><item children-are-sections="no" expanded="yes" state="unchecked"><style><value key="text-background-color"><color r="1" g="1" b="1"/></value></style><values><text><p><run><lit>Fetch</lit></run></p></text></values></item></children><children><item children-are-sections="no" expanded="yes" state="unchecked"><style><value key="text-background-color"><color r="1" g="1" b="1"/></value></style><values><text><p><run><lit>A</lit></run></p></text></values></item></children><children><item children-are-sections="no" expanded="yes" state="unchecked"><style><value key="text-background-color"><color r="1" g="1" b="1"/></value></style><values><text><p><run><lit>Pail</lit></run></p></text></values></item></children><children><item children-are-sections="no" expanded="yes" state="unchecked"><style><value key="text-background-color"><color r="1" g="1" b="1"/></value></style><values><text><p><run><lit>Of</lit></run></p></text></values></item></children><children><item children-are-sections="no" expanded="yes" state="unchecked"><style><value key="text-background-color"><color r="1" g="1" b="1"/></value></style><values><text><p><run><lit>Water</lit></run></p></text></values></item></children></item><item children-are-sections="no" expanded="yes" state="unchecked"><style><value key="text-background-color"><color r="1" g="1" b="1"/></value></style><values><text><p><run><lit>And</lit></run></p></text></values></item><item children-are-sections="no" expanded="yes" state="unchecked"><style><value key="text-background-color"><color r="1" g="1" b="1"/></value></style><values><text><p><run><lit>Jill</lit></run></p></text></values></item><item children-are-sections="no" expanded="yes" state="unchecked"><style><value key="text-background-color"><color r="1" g="1" b="1"/></value></style><values><text><p><run><lit>Went</lit></run></p></text></values></item><item children-are-sections="no" expanded="yes" state="unchecked"><style><value key="text-background-color"><color r="1" g="1" b="1"/></value></style><values><text><p><run><lit>Up</lit></run></p></text></values></item><item children-are-sections="no" expanded="yes" state="unchecked"><style><value key="text-background-color"><color r="1" g="1" b="1"/></value></style><values><text><p><run><lit>The</lit></run></p></text></values></item><item children-are-sections="no" expanded="yes" state="unchecked"><style><value key="text-background-color"><color r="1" g="1" b="1"/></value></style><values><text><p><run><lit>Hill</lit></run></p></text></values></item></root></outline>
